llmasajudge/__init__.py
llmasajudge-0.1.15.dist-info/METADATA
llmasajudge-0.1.15.dist-info/WHEEL
llmasajudge-0.1.15.dist-info/top_level.txt
llmasajudge-0.1.15.dist-info/RECORD
